odoo10_addon_base_kanban_stage_state-10.0.1.0.0.99.dev10-nspkg.pth
odoo/addons/base_kanban_stage_state/README.rst
odoo/addons/base_kanban_stage_state/__init__.py
odoo/addons/base_kanban_stage_state/__manifest__.py
odoo/addons/base_kanban_stage_state/i18n/base_kanban_stage_state.pot
odoo/addons/base_kanban_stage_state/i18n/ca.po
odoo/addons/base_kanban_stage_state/i18n/cs.po
odoo/addons/base_kanban_stage_state/i18n/da.po
odoo/addons/base_kanban_stage_state/i18n/de.po
odoo/addons/base_kanban_stage_state/i18n/es.po
odoo/addons/base_kanban_stage_state/i18n/es_ES.po
odoo/addons/base_kanban_stage_state/i18n/es_MX.po
odoo/addons/base_kanban_stage_state/i18n/es_VE.po
odoo/addons/base_kanban_stage_state/i18n/fi.po
odoo/addons/base_kanban_stage_state/i18n/fr.po
odoo/addons/base_kanban_stage_state/i18n/fr_CH.po
odoo/addons/base_kanban_stage_state/i18n/gl.po
odoo/addons/base_kanban_stage_state/i18n/hr.po
odoo/addons/base_kanban_stage_state/i18n/hr_HR.po
odoo/addons/base_kanban_stage_state/i18n/hu.po
odoo/addons/base_kanban_stage_state/i18n/it.po
odoo/addons/base_kanban_stage_state/i18n/nb.po
odoo/addons/base_kanban_stage_state/i18n/nb_NO.po
odoo/addons/base_kanban_stage_state/i18n/nl.po
odoo/addons/base_kanban_stage_state/i18n/pl.po
odoo/addons/base_kanban_stage_state/i18n/pt.po
odoo/addons/base_kanban_stage_state/i18n/pt_BR.po
odoo/addons/base_kanban_stage_state/i18n/pt_PT.po
odoo/addons/base_kanban_stage_state/i18n/ro.po
odoo/addons/base_kanban_stage_state/i18n/sl.po
odoo/addons/base_kanban_stage_state/i18n/sv.po
odoo/addons/base_kanban_stage_state/i18n/tr.po
odoo/addons/base_kanban_stage_state/i18n/tr_TR.po
odoo/addons/base_kanban_stage_state/i18n/zh_CN.po
odoo/addons/base_kanban_stage_state/models/__init__.py
odoo/addons/base_kanban_stage_state/models/base_kanban_stage.py
odoo/addons/base_kanban_stage_state/static/description/icon.png
odoo/addons/base_kanban_stage_state/tests/__init__.py
odoo/addons/base_kanban_stage_state/tests/test_base_kanban_stage.py
odoo10_addon_base_kanban_stage_state-10.0.1.0.0.99.dev10.dist-info/METADATA
odoo10_addon_base_kanban_stage_state-10.0.1.0.0.99.dev10.dist-info/WHEEL
odoo10_addon_base_kanban_stage_state-10.0.1.0.0.99.dev10.dist-info/namespace_packages.txt
odoo10_addon_base_kanban_stage_state-10.0.1.0.0.99.dev10.dist-info/top_level.txt
odoo10_addon_base_kanban_stage_state-10.0.1.0.0.99.dev10.dist-info/RECORD
