Metadata-Version: 2.1
Name: odoo10-addon-base-kanban-stage-state
Version: 10.0.1.0.0.99.dev10
Summary: Maps stages from base_kanban_stage to states
Home-page: https://odoo-community.org/
Author: SMDrugstore, Odoo Community Association (OCA)
Author-email: support@odoo-community.org
License: LGPL-3
Platform: UNKNOWN
Classifier: Programming Language :: Python
Classifier: Framework :: Odoo
Classifier: License :: OSI Approved :: GNU Lesser General Public License v3 (LGPLv3)
Requires-Python: ~=2.7
Requires-Dist: odoo10-addon-base-kanban-stage
Requires-Dist: odoo (<10.1dev,>=10.0)
